SlashDiscord/__init__.py
SlashDiscord/client/__init__.py
SlashDiscord/client/client.py
SlashDiscord/command/__init__.py
SlashDiscord/command/command.py
SlashDiscord/util/__init__.py
SlashDiscord/util/embed.py
SlashDiscord/util/gateway.py
SlashDiscord/util/interaction.py
SlashDiscord/util/socket.py
SlashDiscord/util/user.py
SlashDiscord-0.3.1.dist-info/LICENSE
SlashDiscord-0.3.1.dist-info/METADATA
SlashDiscord-0.3.1.dist-info/WHEEL
SlashDiscord-0.3.1.dist-info/top_level.txt
SlashDiscord-0.3.1.dist-info/RECORD
