Metadata-Version: 2.1
Name: SlashDiscord
Version: 0.3.1
Summary: Extra lightweight discord slash command library
Home-page: https://github.com/Reppo-Bot/SlashDiscord
Author: Joshua Brown & Matt Dray
Author-email: Josh@Mjbrowns.com
License: GNU GPLv3
Project-URL: Bug Tracker, https://github.com/Reppo-Bot/SlashDiscord/issues
Platform: Any
Classifier: Programming Language :: Python :: 3
Classifier: License :: OSI Approved :: GNU General Public License v3 (GPLv3)
Classifier: Operating System :: OS Independent
Requires-Python: >=3.6
License-File: LICENSE
Requires-Dist: websockets (~=10.2)
Requires-Dist: requests (~=2.27)
